README.txt
setup.py
docs/HISTORY.txt
docs/LICENSE.txt
z3c/__init__.py
z3c.appconfig.egg-info/PKG-INFO
z3c.appconfig.egg-info/SOURCES.txt
z3c.appconfig.egg-info/dependency_links.txt
z3c.appconfig.egg-info/namespace_packages.txt
z3c.appconfig.egg-info/not-zip-safe
z3c.appconfig.egg-info/requires.txt
z3c.appconfig.egg-info/top_level.txt
z3c/appconfig/__init__.py
z3c/appconfig/config.py
z3c/appconfig/interfaces.py
z3c/appconfig/meta.zcml
z3c/appconfig/utils.py
z3c/appconfig/zcml.py
z3c/appconfig/tests/__init__.py
z3c/appconfig/tests/sample.cfg
z3c/appconfig/tests/test_config.py
z3c/appconfig/tests/test_utils.py