Metadata-Version: 1.0
Name: z3c.appconfig
Version: 1.0
Summary: Simple application configuration system
Home-page: http://svn.plone.org/svn/collective/
Author: Wichert Akkerman
Author-email: wichert@wiggy.net
License: BSD
Platform: UNKNOWN
Classifier: Development Status :: 5 - Production/Stable
Classifier: Framework :: Plone
Classifier: Framework :: Zope2
Classifier: Framework :: Zope3
Classifier: Intended Audience :: Developers
Classifier: License :: OSI Approved :: BSD License
Classifier: Operating System :: OS Independent
Classifier: Programming Language :: Python :: 2
Classifier: Topic :: Software Development :: Libraries :: Python Modules
